pytobot/__init__.py
pytobot/__main__.py
pytobot/pytobot.py
pytobot-1.2.1.dist-info/METADATA
pytobot-1.2.1.dist-info/WHEEL
pytobot-1.2.1.dist-info/entry_points.txt
pytobot-1.2.1.dist-info/top_level.txt
pytobot-1.2.1.dist-info/RECORD
