Metadata-Version: 2.1
Name: pytobot
Version: 1.2.1
Summary: Run script as Telegram bot
Home-page: https://github.com/dmitrijkotov634
Author: dmitrijkotov
Author-email: dmitrijkotov634@mail.ru
License: MIT
Platform: UNKNOWN
Classifier: Programming Language :: Python :: 3
Classifier: Programming Language :: Python :: 3.4
Classifier: Programming Language :: Python :: 3.5
Classifier: Programming Language :: Python :: 3.6
Classifier: Programming Language :: Python :: 3.7
Classifier: License :: OSI Approved :: MIT License
Classifier: Operating System :: OS Independent
Requires-Python: >=3
Requires-Dist: requests
